scorem_core.cpython-39-darwin.so
scorem/__init__.py
scorem/assessParticles.py
scorem/displayAngularDistributionStandalone.py
scorem/metrics.py
scorem/particlesDiscriminator.py
scorem/scorem_cmd_caller.py
scorem/scorem_cmd_starProcess.py
scorem/scores.py
scorem/starDisplay.py
scorem/starHandler.py
scorem/utils.py
scorem-0.1.0.dist-info/METADATA
scorem-0.1.0.dist-info/WHEEL
scorem-0.1.0.dist-info/entry_points.txt
scorem-0.1.0.dist-info/top_level.txt
scorem-0.1.0.dist-info/RECORD
