Metadata-Version: 2.1
Name: scorem
Version: 0.1.0
Summary: scorem, library for assessing EM reconstruction from particles scores
Home-page: UNKNOWN
Author: Mauro Maiorca
Author-email: UNKNOWN
License: MIT
Platform: UNKNOWN
